pyrubi/__init__.py
pyrubi/enums.py
pyrubi/exceptions.py
pyrubi/client/__init__.py
pyrubi/client/client.py
pyrubi/crypto/__init__.py
pyrubi/crypto/crypto.py
pyrubi/methods/__init__.py
pyrubi/methods/methods.py
pyrubi/network/__init__.py
pyrubi/network/helper.py
pyrubi/network/network.py
pyrubi/network/socket.py
pyrubi/sessions/__init__.py
pyrubi/sessions/sessions.py
pyrubi/types/__init__.py
pyrubi/types/socket/__init__.py
pyrubi/types/socket/message.py
pyrubi/utils/__init__.py
pyrubi/utils/configs.py
pyrubi/utils/utils.py
pyrubi-3.5.1.dist-info/METADATA
pyrubi-3.5.1.dist-info/WHEEL
pyrubi-3.5.1.dist-info/top_level.txt
pyrubi-3.5.1.dist-info/RECORD
