Metadata-Version: 2.1
Name: pyrubi
Version: 3.5.1
Summary: This is a powerful and easy library for building self bot in the Rubika.
Home-page: https://github.com/AliGanji1/pyrubi
Author: Ali Ganji zadeh
Author-email: ali.ganji.za@gmail.com
Keywords: rubika,rubino,pyrubi,pyrubika,bot,chat
Classifier: Programming Language :: Python :: 3.7
Classifier: Programming Language :: Python :: 3.8
Classifier: Programming Language :: Python :: 3.9
Classifier: Programming Language :: Python :: 3.10
Classifier: Programming Language :: Python :: 3.11
Classifier: Programming Language :: Python :: 3.12
Classifier: License :: OSI Approved :: GNU Lesser General Public License v3 (LGPLv3)
Classifier: Topic :: Internet
Classifier: Topic :: Communications
Classifier: Topic :: Communications :: Chat
Classifier: Topic :: Software Development :: Libraries
Classifier: Topic :: Software Development :: Libraries :: Python Modules
Classifier: Topic :: Software Development :: Libraries :: Application Frameworks
Requires-Python: ~=3.7
Requires-Dist: urllib3
Requires-Dist: tqdm
Requires-Dist: websocket-client
Requires-Dist: pycryptodome
Requires-Dist: mutagen
Requires-Dist: filetype
